uca/__init__.py
uca/__version__.py
uca/constants.py
uca/exceptions.py
uca/main.py
uca/commands/__init__.py
uca/commands/convert.py
uca/common/__init__.py
uca/common/aws.py
uca/common/cli.py
uca/common/custom_types.py
uca/common/files.py
uca/common/formatters.py
uca/common/standards.py
uca/data/alb_configuration.json
uca/data/configuration.json
uca/data/csv_configuration.json
uca/data/data.csv
uca/data/example_alb_logs
uca/data/sample_uca_data.jsonl
uca/data/test_configuration.json
uca/data/test_data.csv
uca/data/transform.jq
uca/features/__init__.py
uca/features/convert.py
uca/features/generate.py
uca/features/transform.py
uca/features/transmit.py
uca/interfaces/__init__.py
uca/interfaces/uca_api.py
uca/vendored/__init__.py
uca/vendored/aws_log_parser/__init__.py
uca/vendored/aws_log_parser/exceptions.py
uca/vendored/aws_log_parser/interface.py
uca/vendored/aws_log_parser/models.py
uca/vendored/aws_log_parser/parser.py
uca/vendored/aws_log_parser/util.py
uca/vendored/aws_log_parser/aws/__init__.py
uca/vendored/aws_log_parser/aws/client.py
uca/vendored/aws_log_parser/aws/plugin.py
uca/vendored/aws_log_parser/aws/s3.py
uca/vendored/aws_log_parser/cli/__init__.py
uca/vendored/aws_log_parser/cli/main.py
cloudzero_uca_tools-0.7.11.dist-info/METADATA
cloudzero_uca_tools-0.7.11.dist-info/WHEEL
cloudzero_uca_tools-0.7.11.dist-info/entry_points.txt
cloudzero_uca_tools-0.7.11.dist-info/licenses/LICENSE
cloudzero_uca_tools-0.7.11.dist-info/RECORD
