Metadata-Version: 2.3
Name: cloudzero-uca-tools
Version: 0.7.11
Summary: CloudZero UCA Toolkit
Project-URL: Homepage, https://github.com/Cloudzero/cloudzero-uca-tools
Author-email: CloudZero <support@cloudzero.com>
License: Apache-2.0
License-File: LICENSE
Keywords: CloudZero,Toolkit,UCA,analysis,cost,economics,unit
Classifier: Development Status :: 4 - Beta
Classifier: Intended Audience :: Developers
Classifier: License :: OSI Approved :: Apache Software License
Classifier: Natural Language :: English
Classifier: Operating System :: MacOS
Classifier: Operating System :: Unix
Classifier: Programming Language :: Python :: 3.9
Requires-Python: >=3.9
Requires-Dist: beautifulsoup4>=4.11.2
Requires-Dist: boto3==1.26.118
Requires-Dist: click>=8.1.3
Requires-Dist: colored>=1.4.4
Requires-Dist: geoip2==4.6.0
Requires-Dist: jq>=1.4.0
Requires-Dist: progressbar>=2.5
Requires-Dist: python-whois==0.8.0
Requires-Dist: requests>=2.28.2
Requires-Dist: rich==13.3.5
Requires-Dist: simplejson>=3.18.3
Requires-Dist: stringcase>=1.2.0
Requires-Dist: tabulate>=0.9.0
Requires-Dist: termcolor>=2.4.0
Requires-Dist: user-agents==2.2.0
